AUTHORS.rst
CONTRIBUTING.rst
HISTORY.rst
LICENSE
MANIFEST.in
README.rst
setup.cfg
setup.py
docs/Makefile
docs/authors.rst
docs/conf.py
docs/contributing.rst
docs/history.rst
docs/index.rst
docs/installation.rst
docs/make.bat
docs/readme.rst
docs/usage.rst
lambda_utils/__init__.py
lambda_utils.egg-info/PKG-INFO
lambda_utils.egg-info/SOURCES.txt
lambda_utils.egg-info/dependency_links.txt
lambda_utils.egg-info/not-zip-safe
lambda_utils.egg-info/top_level.txt
lambda_utils/logger/__init__.py
lambda_utils/logger/sentry.py
lambda_utils/response_handlers/__init__.py
lambda_utils/response_handlers/api_gateway.py
lambda_utils/response_handlers/cloudformation.py
tests/__init__.py
tests/conftest.py
tests/test_lambda_processor.py
tests/logger/__init__.py
tests/logger/test_sentry.py
tests/response_handlers/__init__.py
tests/response_handlers/test_api_gateway.py
tests/response_handlers/test_cloudformation.py