Metadata-Version: 1.1
Name: lambda-utils
Version: 0.2.13
Summary: A collection of AWS Lambda Utils / Decorator for different AWS events e.g. Api Gateway, S3, CloudFormation, CloudWatch 
Home-page: https://github.com/CloudHeads/lambda_utils
Author: Cloudheads
Author-email: theguys@cloudheads.io
License: MIT license
Keywords: lambda_utils
Platform: UNKNOWN
Classifier: Development Status :: 2 - Pre-Alpha
Classifier: Intended Audience :: Developers
Classifier: License :: OSI Approved :: MIT License
Classifier: Natural Language :: English
Classifier: Programming Language :: Python :: 2
Classifier: Programming Language :: Python :: 2.7
